<annotation>
	<folder>Cars</folder>
	<filename>DSC_0989.JPG</filename>
	<path>D:\Car_No_plate_recognition\carnoplate\Pakistani License Number Plates Data\Cars\DSC_0989.JPG</path>
	<source>
		<database>Unknown</database>
	</source>
	<size>
		<width>2425</width>
		<height>1457</height>
		<depth>3</depth>
	</size>
	<segmented>0</segmented>
	<object>
		<name>no_plate</name>
		<pose>Unspecified</pose>
		<truncated>0</truncated>
		<difficult>0</difficult>
		<bndbox>
			<xmin>1421</xmin>
			<ymin>911</ymin>
			<xmax>1783</xmax>
			<ymax>1084</ymax>
		</bndbox>
	</object>
</annotation>
